kube1s/__init__.py
kube1s/scale.py
kube1s-0.5.0.dist-info/METADATA
kube1s-0.5.0.dist-info/WHEEL
kube1s-0.5.0.dist-info/entry_points.txt
kube1s-0.5.0.dist-info/top_level.txt
kube1s-0.5.0.dist-info/RECORD
