Metadata-Version: 2.1
Name: kube1s
Version: 0.5.0
Summary: Default template for PDM package
Author-email: hahahellooo <hahahello777@gmail.com>
License: MIT
Project-URL: Hompage, https://github.com/hahahellooo/kube1s
Project-URL: Issues, https://github.com/hahahellooo/kube1s/issues
Requires-Python: ==3.11.*
